fact/__init__.py
fact/cli.py
fact/lib.py
fact/py.typed
fact_test_001-1.0.0.dist-info/LICENSE.txt
fact_test_001-1.0.0.dist-info/METADATA
fact_test_001-1.0.0.dist-info/WHEEL
fact_test_001-1.0.0.dist-info/entry_points.txt
fact_test_001-1.0.0.dist-info/top_level.txt
fact_test_001-1.0.0.dist-info/RECORD
